aigoo/__init__.py
aigoo/__main__.py
aigoo/aigoo.py
dope/__init__.py
dope/__main__.py
dope/dope.py
aigoo-0.0.2.dist-info/LICENSE
aigoo-0.0.2.dist-info/METADATA
aigoo-0.0.2.dist-info/WHEEL
aigoo-0.0.2.dist-info/entry_points.txt
aigoo-0.0.2.dist-info/top_level.txt
aigoo-0.0.2.dist-info/RECORD
