Metadata-Version: 2.1
Name: aigoo
Version: 0.0.2
Summary: Compiler error solution
Home-page: https://github.com/aditya612/dope
Author: Aditya Agarwal
Author-email: naveenagarwal123451@gmail.com
License: MIT
Platform: UNKNOWN
Classifier: Environment :: Console
Classifier: Intended Audience :: Developers
Classifier: Topic :: Software Development
Classifier: Topic :: Software Development :: Debuggers
Classifier: Natural Language :: English
Classifier: License :: OSI Approved :: MIT License
Classifier: Programming Language :: Python
Requires: BeautifulSoup4
Requires: requests
Requires: urllib3
Requires: tk
Requires: numpy
Requires: pandas
Requires-Dist: BeautifulSoup4
Requires-Dist: requests
Requires-Dist: urllib3
Requires-Dist: tk
Requires-Dist: numpy
Requires-Dist: pandas
